README.rst
setup.py
app_store/__init__.py
app_store/reviews.py
app_store.egg-info/PKG-INFO
app_store.egg-info/SOURCES.txt
app_store.egg-info/dependency_links.txt
app_store.egg-info/requires.txt
app_store.egg-info/top_level.txt