Metadata-Version: 1.1
Name: app-store
Version: 1.0.1
Summary: Utilities for interacting with Apple's iTunes App Store
Home-page: https://github.com/rrueth/app-store
Author: Ryan Rueth
Author-email: rrueth@gmail.com
License: MIT
Keywords: iTunes AppStore
Platform: UNKNOWN
Classifier: Development Status :: 3 - Alpha
Classifier: Intended Audience :: Developers
Classifier: Topic :: Software Development :: Libraries :: Python Modules
Classifier: License :: OSI Approved :: MIT License
Classifier: Programming Language :: Python :: 2.7
Classifier: Programming Language :: Python :: 3.3
Classifier: Programming Language :: Python :: 3.4
Classifier: Programming Language :: Python :: 3.5
